ArduinoCodeCreator/__init__.py
ArduinoCodeCreator/arduino.py
ArduinoCodeCreator/arduino_data_types.py
ArduinoCodeCreator/basic_types.py
ArduinoCodeCreator/code_creator.py
ArduinoCodeCreator/statements.py
ArduinoCodeCreator-0.1.1583235527.dist-info/METADATA
ArduinoCodeCreator-0.1.1583235527.dist-info/WHEEL
ArduinoCodeCreator-0.1.1583235527.dist-info/top_level.txt
ArduinoCodeCreator-0.1.1583235527.dist-info/RECORD
