Metadata-Version: 2.1
Name: ArduinoCodeCreator
Version: 0.1.1583235527
Summary: python code creator for creating arduino code
Home-page: https://github.com/JulianKimmig/ArduinoCodeCreator
Author: Julian Kimmig
Author-email: julian-kimmig@gmx.net
License: UNKNOWN
Platform: UNKNOWN
Classifier: Programming Language :: Python :: 3
Classifier: License :: OSI Approved :: MIT License
Classifier: Operating System :: OS Independent
Requires-Dist: numpy
